{
	"name": "files to sql_raw",
	"properties": {
		"activities": [
			{
				"name": "customer input to consolidated",
				"type": "Copy",
				"dependsOn": [],
				"policy": {
					"timeout": "0.12:00:00",
					"retry": 0,
					"retryIntervalInSeconds": 30,
					"secureOutput": false,
					"secureInput": false
				},
				"userProperties": [],
				"typeProperties": {
					"source": {
						"type": "DelimitedTextSource",
						"storeSettings": {
							"type": "AzureBlobStorageReadSettings",
							"recursive": true,
							"wildcardFolderPath": "assessment_1",
							"wildcardFileName": "*.csv",
							"enablePartitionDiscovery": false
						},
						"formatSettings": {
							"type": "DelimitedTextReadSettings"
						}
					},
					"sink": {
						"type": "DelimitedTextSink",
						"storeSettings": {
							"type": "AzureBlobStorageWriteSettings",
							"copyBehavior": "MergeFiles"
						},
						"formatSettings": {
							"type": "DelimitedTextWriteSettings",
							"quoteAllText": true,
							"fileExtension": ".txt"
						}
					},
					"enableStaging": false,
					"translator": {
						"type": "TabularTranslator",
						"mappings": [
							{
								"source": {
									"name": "CustomerID",
									"type": "String",
									"physicalType": "String"
								},
								"sink": {
									"name": "CustomerID",
									"type": "String",
									"physicalType": "nvarchar"
								}
							},
							{
								"source": {
									"name": "FirstName",
									"type": "String",
									"physicalType": "String"
								},
								"sink": {
									"name": "FirstName",
									"type": "String",
									"physicalType": "nvarchar"
								}
							},
							{
								"source": {
									"name": "LastName",
									"type": "String",
									"physicalType": "String"
								},
								"sink": {
									"name": "LastName",
									"type": "String",
									"physicalType": "nvarchar"
								}
							},
							{
								"source": {
									"name": "Email",
									"type": "String",
									"physicalType": "String"
								},
								"sink": {
									"name": "Email",
									"type": "String",
									"physicalType": "nvarchar"
								}
							},
							{
								"source": {
									"name": "PhoneNumber",
									"type": "String",
									"physicalType": "String"
								},
								"sink": {
									"name": "PhoneNumber",
									"type": "String",
									"physicalType": "nvarchar"
								}
							},
							{
								"source": {
									"name": "Address",
									"type": "String",
									"physicalType": "String"
								},
								"sink": {
									"name": "Address",
									"type": "String",
									"physicalType": "nvarchar"
								}
							},
							{
								"source": {
									"name": "City",
									"type": "String",
									"physicalType": "String"
								},
								"sink": {
									"name": "City",
									"type": "String",
									"physicalType": "nvarchar"
								}
							},
							{
								"source": {
									"name": "State",
									"type": "String",
									"physicalType": "String"
								},
								"sink": {
									"name": "State",
									"type": "String",
									"physicalType": "nvarchar"
								}
							},
							{
								"source": {
									"name": "ZipCode",
									"type": "String",
									"physicalType": "String"
								},
								"sink": {
									"name": "ZipCode",
									"type": "String",
									"physicalType": "nvarchar"
								}
							},
							{
								"source": {
									"name": "Country",
									"type": "String",
									"physicalType": "String"
								},
								"sink": {
									"name": "Country",
									"type": "String",
									"physicalType": "nvarchar"
								}
							}
						],
						"typeConversion": true,
						"typeConversionSettings": {
							"allowDataTruncation": true,
							"treatBooleanAsNumber": false
						}
					}
				},
				"inputs": [
					{
						"referenceName": "cust_csv",
						"type": "DatasetReference"
					}
				],
				"outputs": [
					{
						"referenceName": "consolidated_customer",
						"type": "DatasetReference"
					}
				]
			},
			{
				"name": "order input to consolidated",
				"type": "Copy",
				"dependsOn": [],
				"policy": {
					"timeout": "0.12:00:00",
					"retry": 0,
					"retryIntervalInSeconds": 30,
					"secureOutput": false,
					"secureInput": false
				},
				"userProperties": [],
				"typeProperties": {
					"source": {
						"type": "ExcelSource",
						"storeSettings": {
							"type": "AzureBlobStorageReadSettings",
							"recursive": true,
							"wildcardFolderPath": "assessment_1",
							"wildcardFileName": "*.xlsx",
							"enablePartitionDiscovery": false
						}
					},
					"sink": {
						"type": "DelimitedTextSink",
						"storeSettings": {
							"type": "AzureBlobStorageWriteSettings",
							"copyBehavior": "MergeFiles"
						},
						"formatSettings": {
							"type": "DelimitedTextWriteSettings",
							"quoteAllText": true,
							"fileExtension": ".txt"
						}
					},
					"enableStaging": false,
					"translator": {
						"type": "TabularTranslator",
						"typeConversion": true,
						"typeConversionSettings": {
							"allowDataTruncation": true,
							"treatBooleanAsNumber": false
						}
					}
				},
				"inputs": [
					{
						"referenceName": "order_xlsx",
						"type": "DatasetReference"
					}
				],
				"outputs": [
					{
						"referenceName": "consolidated_order",
						"type": "DatasetReference"
					}
				]
			},
			{
				"name": "consolidated order to staging area",
				"type": "Copy",
				"dependsOn": [
					{
						"activity": "order input to consolidated",
						"dependencyConditions": [
							"Succeeded"
						]
					}
				],
				"policy": {
					"timeout": "0.12:00:00",
					"retry": 0,
					"retryIntervalInSeconds": 30,
					"secureOutput": false,
					"secureInput": false
				},
				"userProperties": [],
				"typeProperties": {
					"source": {
						"type": "DelimitedTextSource",
						"storeSettings": {
							"type": "AzureBlobStorageReadSettings",
							"recursive": true,
							"wildcardFolderPath": "order",
							"wildcardFileName": "*.csv",
							"enablePartitionDiscovery": false
						},
						"formatSettings": {
							"type": "DelimitedTextReadSettings"
						}
					},
					"sink": {
						"type": "AzureSqlSink",
						"preCopyScript": "DROP TABLE IF EXISTS [raw].[order]",
						"writeBehavior": "insert",
						"sqlWriterUseTableLock": false,
						"tableOption": "autoCreate",
						"disableMetricsCollection": false
					},
					"enableStaging": false,
					"translator": {
						"type": "TabularTranslator",
						"typeConversion": true,
						"typeConversionSettings": {
							"allowDataTruncation": true,
							"treatBooleanAsNumber": false
						}
					}
				},
				"inputs": [
					{
						"referenceName": "consolidated_order",
						"type": "DatasetReference"
					}
				],
				"outputs": [
					{
						"referenceName": "sql_raw_order",
						"type": "DatasetReference"
					}
				]
			},
			{
				"name": "consolidated customer to staging area",
				"type": "Copy",
				"dependsOn": [
					{
						"activity": "customer input to consolidated",
						"dependencyConditions": [
							"Succeeded"
						]
					}
				],
				"policy": {
					"timeout": "0.12:00:00",
					"retry": 0,
					"retryIntervalInSeconds": 30,
					"secureOutput": false,
					"secureInput": false
				},
				"userProperties": [],
				"typeProperties": {
					"source": {
						"type": "DelimitedTextSource",
						"storeSettings": {
							"type": "AzureBlobStorageReadSettings",
							"recursive": true,
							"wildcardFolderPath": "customer",
							"wildcardFileName": "*.csv",
							"enablePartitionDiscovery": false
						},
						"formatSettings": {
							"type": "DelimitedTextReadSettings"
						}
					},
					"sink": {
						"type": "AzureSqlSink",
						"preCopyScript": "DROP TABLE IF EXISTS [raw].[customer]",
						"writeBehavior": "insert",
						"sqlWriterUseTableLock": false,
						"tableOption": "autoCreate",
						"disableMetricsCollection": false
					},
					"enableStaging": false,
					"translator": {
						"type": "TabularTranslator",
						"mappings": [
							{
								"source": {
									"name": "CustomerID",
									"type": "String",
									"physicalType": "String"
								},
								"sink": {
									"name": "CustomerID",
									"type": "String",
									"physicalType": "nvarchar"
								}
							},
							{
								"source": {
									"name": "FirstName",
									"type": "String",
									"physicalType": "String"
								},
								"sink": {
									"name": "FirstName",
									"type": "String",
									"physicalType": "nvarchar"
								}
							},
							{
								"source": {
									"name": "LastName",
									"type": "String",
									"physicalType": "String"
								},
								"sink": {
									"name": "LastName",
									"type": "String",
									"physicalType": "nvarchar"
								}
							},
							{
								"source": {
									"name": "Email",
									"type": "String",
									"physicalType": "String"
								},
								"sink": {
									"name": "Email",
									"type": "String",
									"physicalType": "nvarchar"
								}
							},
							{
								"source": {
									"name": "PhoneNumber",
									"type": "String",
									"physicalType": "String"
								},
								"sink": {
									"name": "PhoneNumber",
									"type": "String",
									"physicalType": "nvarchar"
								}
							},
							{
								"source": {
									"name": "Address",
									"type": "String",
									"physicalType": "String"
								},
								"sink": {
									"name": "Address",
									"type": "String",
									"physicalType": "nvarchar"
								}
							},
							{
								"source": {
									"name": "City",
									"type": "String",
									"physicalType": "String"
								},
								"sink": {
									"name": "City",
									"type": "String",
									"physicalType": "nvarchar"
								}
							},
							{
								"source": {
									"name": "State",
									"type": "String",
									"physicalType": "String"
								},
								"sink": {
									"name": "State",
									"type": "String",
									"physicalType": "nvarchar"
								}
							},
							{
								"source": {
									"name": "ZipCode",
									"type": "String",
									"physicalType": "String"
								},
								"sink": {
									"name": "ZipCode",
									"type": "String",
									"physicalType": "nvarchar"
								}
							},
							{
								"source": {
									"name": "Country",
									"type": "String",
									"physicalType": "String"
								},
								"sink": {
									"name": "Country",
									"type": "String",
									"physicalType": "nvarchar"
								}
							}
						],
						"typeConversion": true,
						"typeConversionSettings": {
							"allowDataTruncation": true,
							"treatBooleanAsNumber": false
						}
					}
				},
				"inputs": [
					{
						"referenceName": "consolidated_customer",
						"type": "DatasetReference"
					}
				],
				"outputs": [
					{
						"referenceName": "sql_raw_cust",
						"type": "DatasetReference"
					}
				]
			}
		],
		"folder": {
			"name": "others"
		},
		"annotations": [],
		"lastPublishTime": "2024-08-27T08:10:01Z"
	},
	"type": "Microsoft.DataFactory/factories/pipelines"
}